<!-- 战魂升级配置表 -->
<root>
	<levelup rank="1" lv="0" exp="80" />
	<levelup rank="1" lv="1" exp="160" />
	<levelup rank="1" lv="2" exp="240" />
	<levelup rank="1" lv="3" exp="320" />
	<levelup rank="1" lv="4" exp="400" />
	<levelup rank="1" lv="5" exp="480" />
	<levelup rank="1" lv="6" exp="560" />
	<levelup rank="1" lv="7" exp="640" />
	<levelup rank="1" lv="8" exp="720" />
	<levelup rank="1" lv="9" exp="800" />
	<levelup rank="1" lv="10" exp="880" />
	<levelup rank="1" lv="11" exp="960" />
	<levelup rank="1" lv="12" exp="1040" />
	<levelup rank="1" lv="13" exp="1120" />
	<levelup rank="1" lv="14" exp="1200" />
	<levelup rank="1" lv="15" exp="1280" />
	<levelup rank="1" lv="16" exp="1360" />
	<levelup rank="1" lv="17" exp="1440" />
	<levelup rank="1" lv="18" exp="1520" />
	<levelup rank="1" lv="19" exp="1600" />
	<levelup rank="1" lv="20" exp="1680" />
	<levelup rank="1" lv="21" exp="1760" />
	<levelup rank="1" lv="22" exp="1840" />
	<levelup rank="1" lv="23" exp="1920" />
	<levelup rank="1" lv="24" exp="2000" />
	<levelup rank="1" lv="25" exp="2080" />
	<levelup rank="1" lv="26" exp="2160" />
	<levelup rank="1" lv="27" exp="2240" />
	<levelup rank="1" lv="28" exp="2320" />
	<levelup rank="1" lv="29" exp="2400" />
	<levelup rank="1" lv="30" exp="2480" />
	<levelup rank="1" lv="31" exp="2560" />
	<levelup rank="1" lv="32" exp="2640" />
	<levelup rank="1" lv="33" exp="2720" />
	<levelup rank="1" lv="34" exp="2800" />
	<levelup rank="1" lv="35" exp="2880" />
	<levelup rank="1" lv="36" exp="2960" />
	<levelup rank="1" lv="37" exp="3040" />
	<levelup rank="1" lv="38" exp="3120" />
	<levelup rank="1" lv="39" exp="3200" />
	<levelup rank="2" lv="0" exp="115" />
	<levelup rank="2" lv="1" exp="230" />
	<levelup rank="2" lv="2" exp="345" />
	<levelup rank="2" lv="3" exp="460" />
	<levelup rank="2" lv="4" exp="575" />
	<levelup rank="2" lv="5" exp="690" />
	<levelup rank="2" lv="6" exp="805" />
	<levelup rank="2" lv="7" exp="920" />
	<levelup rank="2" lv="8" exp="1035" />
	<levelup rank="2" lv="9" exp="1150" />
	<levelup rank="2" lv="10" exp="1265" />
	<levelup rank="2" lv="11" exp="1380" />
	<levelup rank="2" lv="12" exp="1495" />
	<levelup rank="2" lv="13" exp="1610" />
	<levelup rank="2" lv="14" exp="1725" />
	<levelup rank="2" lv="15" exp="1840" />
	<levelup rank="2" lv="16" exp="1955" />
	<levelup rank="2" lv="17" exp="2070" />
	<levelup rank="2" lv="18" exp="2185" />
	<levelup rank="2" lv="19" exp="2300" />
	<levelup rank="2" lv="20" exp="2415" />
	<levelup rank="2" lv="21" exp="2530" />
	<levelup rank="2" lv="22" exp="2645" />
	<levelup rank="2" lv="23" exp="2760" />
	<levelup rank="2" lv="24" exp="2875" />
	<levelup rank="2" lv="25" exp="2990" />
	<levelup rank="2" lv="26" exp="3105" />
	<levelup rank="2" lv="27" exp="3220" />
	<levelup rank="2" lv="28" exp="3335" />
	<levelup rank="2" lv="29" exp="3450" />
	<levelup rank="2" lv="30" exp="3565" />
	<levelup rank="2" lv="31" exp="3680" />
	<levelup rank="2" lv="32" exp="3795" />
	<levelup rank="2" lv="33" exp="3910" />
	<levelup rank="2" lv="34" exp="4025" />
	<levelup rank="2" lv="35" exp="4140" />
	<levelup rank="2" lv="36" exp="4255" />
	<levelup rank="2" lv="37" exp="4370" />
	<levelup rank="2" lv="38" exp="4485" />
	<levelup rank="2" lv="39" exp="4600" />
	<levelup rank="3" lv="0" exp="150" />
	<levelup rank="3" lv="1" exp="300" />
	<levelup rank="3" lv="2" exp="450" />
	<levelup rank="3" lv="3" exp="600" />
	<levelup rank="3" lv="4" exp="750" />
	<levelup rank="3" lv="5" exp="900" />
	<levelup rank="3" lv="6" exp="1050" />
	<levelup rank="3" lv="7" exp="1200" />
	<levelup rank="3" lv="8" exp="1350" />
	<levelup rank="3" lv="9" exp="1500" />
	<levelup rank="3" lv="10" exp="1650" />
	<levelup rank="3" lv="11" exp="1800" />
	<levelup rank="3" lv="12" exp="1950" />
	<levelup rank="3" lv="13" exp="2100" />
	<levelup rank="3" lv="14" exp="2250" />
	<levelup rank="3" lv="15" exp="2400" />
	<levelup rank="3" lv="16" exp="2550" />
	<levelup rank="3" lv="17" exp="2700" />
	<levelup rank="3" lv="18" exp="2850" />
	<levelup rank="3" lv="19" exp="3000" />
	<levelup rank="3" lv="20" exp="3150" />
	<levelup rank="3" lv="21" exp="3300" />
	<levelup rank="3" lv="22" exp="3450" />
	<levelup rank="3" lv="23" exp="3600" />
	<levelup rank="3" lv="24" exp="3750" />
	<levelup rank="3" lv="25" exp="3900" />
	<levelup rank="3" lv="26" exp="4050" />
	<levelup rank="3" lv="27" exp="4200" />
	<levelup rank="3" lv="28" exp="4350" />
	<levelup rank="3" lv="29" exp="4500" />
	<levelup rank="3" lv="30" exp="4650" />
	<levelup rank="3" lv="31" exp="4800" />
	<levelup rank="3" lv="32" exp="4950" />
	<levelup rank="3" lv="33" exp="5100" />
	<levelup rank="3" lv="34" exp="5250" />
	<levelup rank="3" lv="35" exp="5400" />
	<levelup rank="3" lv="36" exp="5550" />
	<levelup rank="3" lv="37" exp="5700" />
	<levelup rank="3" lv="38" exp="5850" />
	<levelup rank="3" lv="39" exp="6000" />
	<levelup rank="4" lv="0" exp="220" />
	<levelup rank="4" lv="1" exp="440" />
	<levelup rank="4" lv="2" exp="660" />
	<levelup rank="4" lv="3" exp="880" />
	<levelup rank="4" lv="4" exp="1100" />
	<levelup rank="4" lv="5" exp="1320" />
	<levelup rank="4" lv="6" exp="1540" />
	<levelup rank="4" lv="7" exp="1760" />
	<levelup rank="4" lv="8" exp="1980" />
	<levelup rank="4" lv="9" exp="2200" />
	<levelup rank="4" lv="10" exp="2420" />
	<levelup rank="4" lv="11" exp="2640" />
	<levelup rank="4" lv="12" exp="2860" />
	<levelup rank="4" lv="13" exp="3080" />
	<levelup rank="4" lv="14" exp="3300" />
	<levelup rank="4" lv="15" exp="3520" />
	<levelup rank="4" lv="16" exp="3740" />
	<levelup rank="4" lv="17" exp="3960" />
	<levelup rank="4" lv="18" exp="4180" />
	<levelup rank="4" lv="19" exp="4400" />
	<levelup rank="4" lv="20" exp="4620" />
	<levelup rank="4" lv="21" exp="4840" />
	<levelup rank="4" lv="22" exp="5060" />
	<levelup rank="4" lv="23" exp="5280" />
	<levelup rank="4" lv="24" exp="5500" />
	<levelup rank="4" lv="25" exp="5720" />
	<levelup rank="4" lv="26" exp="5940" />
	<levelup rank="4" lv="27" exp="6160" />
	<levelup rank="4" lv="28" exp="6380" />
	<levelup rank="4" lv="29" exp="6600" />
	<levelup rank="4" lv="30" exp="6820" />
	<levelup rank="4" lv="31" exp="7040" />
	<levelup rank="4" lv="32" exp="7260" />
	<levelup rank="4" lv="33" exp="7480" />
	<levelup rank="4" lv="34" exp="7700" />
	<levelup rank="4" lv="35" exp="7920" />
	<levelup rank="4" lv="36" exp="8140" />
	<levelup rank="4" lv="37" exp="8360" />
	<levelup rank="4" lv="38" exp="8580" />
	<levelup rank="4" lv="39" exp="8800" />
</root>
